udlr/__init__.pxd
udlr/__init__.py
udlr/py.typed
udlr/.dylibs/libstdc++.6.dylib
udlr/.dylibs/libgcc_s.1.1.dylib
udlr/gf2sparse/_gf2sparse.pyx
udlr/gf2sparse/__init__.pyi
udlr/gf2sparse/__init__.pxd
udlr/gf2sparse/__init__.py
udlr/gf2sparse/_gf2sparse.cpython-39-darwin.so
udlr/gf2sparse/py.typed
udlr/gf2sparse/_gf2sparse.cpp
udlr/gf2sparse/_gf2sparse.pxd
udlr-0.0.5.dist-info/RECORD
udlr-0.0.5.dist-info/LICENSE
udlr-0.0.5.dist-info/WHEEL
udlr-0.0.5.dist-info/top_level.txt
udlr-0.0.5.dist-info/METADATA
