Metadata-Version: 2.1
Name: udlr
Version: 0.0.5
Summary: A C++ Sparse Matrix Library
Author-email: Joschka Roffe <joschka@roffe.eu>
License: MIT License
Classifier: Development Status :: 4 - Beta
Requires-Python: >=3.8
License-File: LICENSE
Requires-Dist: numpy>=1.24.0
Requires-Dist: scipy>=1.9.3
